MANIFEST.in
PluginShortcutManager.py
README.rst
setup.cfg
setup.py
scribes/__init__.py
scribes.editor.shortcut_manager.egg-info/PKG-INFO
scribes.editor.shortcut_manager.egg-info/SOURCES.txt
scribes.editor.shortcut_manager.egg-info/dependency_links.txt
scribes.editor.shortcut_manager.egg-info/namespace_packages.txt
scribes.editor.shortcut_manager.egg-info/not-zip-safe
scribes.editor.shortcut_manager.egg-info/requires.txt
scribes.editor.shortcut_manager.egg-info/top_level.txt
scribes/editor/__init__.py
scribes/editor/shortcut_manager/__init__.py
scribes/editor/shortcut_manager/gui.glade