Metadata-Version: 1.0
Name: scribes.editor.shortcut-manager
Version: 0.2.3
Summary: Shortcut manager for scribes editor
Home-page: http://github.com/baverman/scribes-goodies
Author: Anton Bobrov
Author-email: bobrov@vl.ru
License: UNKNOWN
Platform: UNKNOWN
